proliantutils/__init__.py
proliantutils/exception.py
proliantutils/log.py
proliantutils/utils.py
proliantutils/functests/__init__.py
proliantutils/functests/test_hpssa.py
proliantutils/hpssa/__init__.py
proliantutils/hpssa/constants.py
proliantutils/hpssa/disk_allocator.py
proliantutils/hpssa/manager.py
proliantutils/hpssa/objects.py
proliantutils/hpssa/raid_config_schema.json
proliantutils/ilo/__init__.py
proliantutils/ilo/client.py
proliantutils/ilo/common.py
proliantutils/ilo/constants.py
proliantutils/ilo/firmware_controller.py
proliantutils/ilo/ipmi.py
proliantutils/ilo/mappings.py
proliantutils/ilo/operations.py
proliantutils/ilo/ribcl.py
proliantutils/ilo/ris.py
proliantutils/ilo/snmp/__init__.py
proliantutils/ilo/snmp/snmp_cpqdisk_sizes.py
proliantutils/ilo/snmp/cpqdisk_mibs/CPQHOST-MIB.py
proliantutils/ilo/snmp/cpqdisk_mibs/CPQIDA-MIB.py
proliantutils/ilo/snmp/cpqdisk_mibs/CPQSCSI-MIB.py
proliantutils/ilo/snmp/cpqdisk_mibs/IANAifType-MIB.py
proliantutils/ilo/snmp/cpqdisk_mibs/IF-MIB.py
proliantutils/ilo/snmp/cpqdisk_mibs/RFC1215-MIB.py
proliantutils/ipa_hw_manager/__init__.py
proliantutils/ipa_hw_manager/hardware_manager.py
proliantutils/redfish/__init__.py
proliantutils/redfish/connector.py
proliantutils/redfish/main.py
proliantutils/redfish/redfish.py
proliantutils/redfish/utils.py
proliantutils/redfish/resources/__init__.py
proliantutils/redfish/resources/gpu_common.py
proliantutils/redfish/resources/update_service.py
proliantutils/redfish/resources/account_service/__init__.py
proliantutils/redfish/resources/account_service/account.py
proliantutils/redfish/resources/account_service/account_service.py
proliantutils/redfish/resources/chassis/__init__.py
proliantutils/redfish/resources/chassis/chassis.py
proliantutils/redfish/resources/chassis/devices.py
proliantutils/redfish/resources/manager/__init__.py
proliantutils/redfish/resources/manager/constants.py
proliantutils/redfish/resources/manager/https_cert.py
proliantutils-2.16.3.dist-info/AUTHORS
proliantutils-2.16.3.dist-info/LICENSE
proliantutils-2.16.3.dist-info/METADATA
proliantutils-2.16.3.dist-info/WHEEL
proliantutils-2.16.3.dist-info/entry_points.txt
proliantutils-2.16.3.dist-info/pbr.json
proliantutils-2.16.3.dist-info/top_level.txt
proliantutils-2.16.3.dist-info/RECORD
