Metadata-Version: 2.1
Name: proliantutils
Version: 2.16.3
Summary: Client Library for interfacing with various devices in HP Proliant Servers.
Home-page: https://opendev.org/x/proliantutils
Author: Hewlett Packard Enterprise
Author-email: proliantutils@gmail.com
License: Apache License, Version 2.0
Platform: UNKNOWN
Classifier: Development Status :: 4 - Beta
Classifier: Environment :: Console
Classifier: Environment :: Web Environment
Classifier: Intended Audience :: Developers
Classifier: Intended Audience :: Information Technology
Classifier: License :: OSI Approved :: Apache Software License
Classifier: Operating System :: OS Independent
Classifier: Programming Language :: Python
Classifier: Programming Language :: Python :: 3
Classifier: Programming Language :: Python :: 3 :: Only
Classifier: Programming Language :: Python :: 3.8
Classifier: Programming Language :: Python :: 3.9
Requires-Python: >=3.6
Requires-Dist: jsonschema (>=2.6.0)
Requires-Dist: oslo.concurrency (>=3.8.0)
Requires-Dist: oslo.serialization (>=1.10.0)
Requires-Dist: oslo.utils (>=3.20.0)
Requires-Dist: pbr (>=2.0.0)
Requires-Dist: pyOpenSSL (>=19.1.0)
Requires-Dist: pyasn1-modules (>=0.3.0)
Requires-Dist: pyasn1 (>=0.5.1)
Requires-Dist: pysnmp-lextudio (>=5.0.0)
Requires-Dist: requests (!=2.12.2,!=2.13.0,>=2.10.0)
Requires-Dist: retrying (!=1.3.0,>=1.2.3)
Requires-Dist: six (>=1.9.0)
Requires-Dist: sushy (>=4.5.2)
